uh_custom_logger/CustomFormatter.py
uh_custom_logger/Logger.py
uh_custom_logger/__init__.py
uh_custom_logger/str_tool.py
uh_custom_logger-0.0.4.dist-info/METADATA
uh_custom_logger-0.0.4.dist-info/WHEEL
uh_custom_logger-0.0.4.dist-info/top_level.txt
uh_custom_logger-0.0.4.dist-info/RECORD
