Metadata-Version: 2.1
Name: uh-custom-logger
Version: 0.0.4
Summary: A custom logging utility for uh projects.
Author: Necip Asik
Author-email: data@universityhousing.nl
